<?xml version="1.0" encoding="UTF-8"?>
<!DOCTYPE configuration PUBLIC "-//mybatis.org//DTD Config 3.0//EN" "http://mybatis.org/dtd/mybatis-3-config.dtd" >
<configuration>

<typeAliases>
	<typeAlias type="com.two.crm.dto.UserDto" alias="UDto"/>
	<typeAlias type="com.two.crm.dto.BoardDto" alias="bDto"/>
	<typeAlias type="com.two.crm.dto.ClientDto" alias="cDto"/>
	<typeAlias type="com.two.crm.dto.GoodsDto" alias="gDto"/>
	<typeAlias type="com.two.crm.dto.ContractDto" alias="ctDto"/>
	<typeAlias type="com.two.crm.dto.BackupDto" alias="bkDto"/>
</typeAliases>


<mappers>
	<mapper resource="/sqls/login.xml"/>
	<mapper resource="/sqls/board.xml"/>
	<mapper resource="/sqls/client.xml"/>
	<mapper resource="/sqls/goods.xml"/>
	<mapper resource="/sqls/users.xml"/>
	<mapper resource="/sqls/chart.xml"/>
	<mapper resource="/sqls/backup.xml"/>
</mappers>

</configuration>
